README.md
setup.py
qth_ls/__init__.py
qth_ls/version.py
qth_ls.egg-info/PKG-INFO
qth_ls.egg-info/SOURCES.txt
qth_ls.egg-info/dependency_links.txt
qth_ls.egg-info/requires.txt
qth_ls.egg-info/top_level.txt