Metadata-Version: 1.1
Name: qth-ls
Version: 0.1.0
Summary: Library for watching paths in the Qth meta/ls/ tree.
Home-page: https://github.com/mossblaser/qth_ls
Author: Jonathan Heathcote
Author-email: UNKNOWN
License: GPLv2
Keywords: mqtt asyncio home-automation messaging
Platform: UNKNOWN
Classifier: Development Status :: 3 - Alpha
Classifier: Intended Audience :: Developers
Classifier: License :: OSI Approved :: GNU General Public License v2 (GPLv2)
Classifier: Operating System :: POSIX :: Linux
Classifier: Operating System :: Microsoft :: Windows
Classifier: Operating System :: MacOS
Classifier: Programming Language :: Python :: 3
Classifier: Programming Language :: Python :: 3.4
Classifier: Programming Language :: Python :: 3.5
